MANIFEST.in
requirements.txt
setup.cfg
setup.py
hashstore/__init__.py
hashstore/base_x.py
hashstore/client.py
hashstore/db.py
hashstore/dir_scan.py
hashstore/local_store.py
hashstore/mount.py
hashstore/mymime.py
hashstore/py2.py
hashstore/server.py
hashstore/session.py
hashstore/shash.py
hashstore/shashd.py
hashstore/udk.py
hashstore/utils.py
hashstore.egg-info/PKG-INFO
hashstore.egg-info/SOURCES.txt
hashstore.egg-info/dependency_links.txt
hashstore.egg-info/entry_points.txt
hashstore.egg-info/not-zip-safe
hashstore.egg-info/requires.txt
hashstore.egg-info/top_level.txt
hashstore/app/fontawesome-webfont.eot
hashstore/app/fontawesome-webfont.svg
hashstore/app/fontawesome-webfont.ttf
hashstore/app/fontawesome-webfont.woff
hashstore/app/fontawesome-webfont.woff2
hashstore/app/glyphicons-halflings-regular.eot
hashstore/app/glyphicons-halflings-regular.svg
hashstore/app/glyphicons-halflings-regular.ttf
hashstore/app/glyphicons-halflings-regular.woff
hashstore/app/glyphicons-halflings-regular.woff2
hashstore/app/hashstore.js
hashstore/app/hashstore.js.map
hashstore/app/index.html
hashstore/app/tests.html