Metadata-Version: 1.1
Name: hashstore
Version: 0.0.12
Summary: Content Addressable Storage
Home-page: https://github.com/walnutgeek/hashstore
Author: Walnut Geek
Author-email: wg@walnutgeek.com
License: Apache 2.0
Platform: UNKNOWN
Classifier: Development Status :: 3 - Alpha
Classifier: Intended Audience :: Developers
Classifier: Topic :: System :: Archiving :: Backup
Classifier: License :: OSI Approved :: Apache Software License
Classifier: Programming Language :: Python :: 2
Classifier: Programming Language :: Python :: 2.7
Classifier: Programming Language :: Python :: 3
Classifier: Programming Language :: Python :: 3.6
